{"url": "https://www.ics.uci.edu/community/news/view_news?id=1694", "word_count": 413, "words": ["ICS", "News", "Archive", "-", "UC", "Irvine", "Donald", "Bren", "School", "of", "Information", "&", "Computer", "Sciences", "If", "looking", "for", "the", "latest", "news,", "go", "here", "\u2026", "Return", "to", "News", "Archive", "List", "January", "23,", "2020", "Still", "Sorting", "Things", "Out:", "Conference", "Honors", "Legacy", "of", "Book", "Coauthored", "by", "Professor", "Bowker", "Last", "month,", "Informatics", "Professor", "Geoffrey", "Bowker", "attended", "a", "unique", "conference", "in", "Paris", "called", "\u201cA", "Book", "Defying", "Classification:", "Sorting", "Things", "Out", "\u2019s", "Legacy,", "20", "Years", "After.\u201d", "The", "event,", "held", "Dec.", "19,", "2019,", "celebrated", "Sorting", "Things", "Out", ":", "Classification", "and", "its", "Consequences", ",", "a", "book", "coauthored", "by", "Bowker", "and", "the", "late", "Susan", "Leigh", "Star", "in", "1999.", "\u201cIt", "felt", "very", "strange", "to", "be", "the", "guest", "of", "honor,\u201d", "admits", "Bowker.", "\u201cI", "am", "much", "more", "used", "to", "discussing", "the", "work", "of", "other", "people", "than", "having", "mine", "discussed.\u201d", "Yet", "delighted", "by", "continued", "interest", "in", "the", "work", "and", "the", "recent", "French", "translation", "of", "the", "book,", "he", "delivered", "the", "keynote", "and", "participated", "in", "a", "roundtable", "discussion", "focused", "on", "the", "book", "and", "its", "influence", "on", "Science", "and", "Technology", "Studies", "(STS).", "Geoffrey", "Bowker", "(left)", "at", "the", "roundtable", "discussion", "focused", "on", "his", "book", "and", "its", "influence", "on", "Science", "and", "Technology", "Studies.", "Sorting", "Things", "Out", "is", "considered", "a", "landmark", "in", "the", "fields", "of", "STS", "and", "sociology", "in", "general,", "though", "it", "is", "lesser", "known", "in", "France.", "\u201c[The", "conference]", "came", "about", "through", "some", "French", "colleagues", "translating", "[the", "book],\u201d", "says", "Bowker.", "\u201cWhile", "the", "book", "is", "well", "known", "in", "the", "anglophone", "world,", "the", "organizers", "felt", "that", "it", "was", "not", "sufficiently", "appreciated", "in", "France.\u201d", "The", "work", "is", "an", "exploration", "of", "the", "role", "that", "categories", "and", "standards", "have", "played", "in", "shaping", "the", "modern", "world,", "producing", "both", "advantage", "and", "suffering.", "Bowker", "recognizes", "that,", "in", "recent", "years,", "the", "need", "for", "classification", "systems", "has", "been", "questioned.", "\u201cThe", "rise", "of", "data", "science", "has", "been", "taken", "to", "mean", "that", "we", "don\u2019t", "need", "the", "clunky", "old", "systems", "which", "put", "things", "manually", "into", "boxes,\u201d", "he", "says,", "though", "he", "argues", "that", "this", "is", "not", "the", "case.", "\u201cThe", "work", "of", "classification", "continues", "unabated", "\u2014", "and", "has", "just", "as", "much", "influence", "in", "terms", "of", "human", "potential", "and", "suffering", "\u2014", "it\u2019s", "just", "buried", "into", "systems", "in", "ways", "that", "most", "users", "find", "difficult", "to", "access.\u201d", "In", "his", "keynote", "at", "the", "conference,", "Bowker", "discussed", "the", "issue", "of", "classification", "as", "it", "relates", "to", "current", "issues.", "\u201cI", "drew", "especially", "on", "issues", "of", "environmental", "sustainability,\u201d", "he", "explains,", "\u201carguing", "that", "the", "ways", "in", "which", "we", "classify", "the", "world", "are", "enormously", "consequential", "for", "the", "ways", "in", "which", "we", "deal", "with", "issues", "such", "as", "climate", "change", "and", "the", "biodiversity", "crisis.\u201d", "\u2014", "Shani", "Murray", "Skip", "to", "content"], "content_hash": "84241b7ded5afb7cc25c0e461f095510"}