{"url": "http://www.ics.uci.edu/~fowlkes", "word_count": 1310, "words": ["charle", "c.", "fowlke", "-", "uc", "irvine", "-", "computer", "vi", "ion", "charle", "c.", "fowlke", "profe", "or", "computer", "cience", "uc", "irvine", "fowlke", "@uci", "4076", "dbh", "949.824.6945", "uci", ":", "c", ":", "vi", "ion", "group", "home", "publication", "pre", "entation", "cv", "My", "re", "earch", "i", "in", "computational", "vi", "ion,", "in", "particular", "how", "to", "integrate", "mechani", "m", "for", "vi", "ual", "recognition", "and", "perceptual", "organization", "with", "3D", "cene", "under", "tanding", ".", "We", "apply", "the", "e", "computational", "model", "to", "a", "variety", "of", "problem", "including", "development", "of", "tool", "for", "biological", "image", "and", "hape", "analy", "i", "in", "neuro", "cience,", "animal", "development", "and", "palynology", "a", "well", "a", "application", "to", "foren", "ic", "cience", ".", "ome", "re", "earch", "highlight", ":", "S.", "Shafique,", "S.", "Kong,", "C.", "Fowlke", ",", "\"CriSp:", "Leveraging", "Tread", "Depth", "Map", "for", "Enhanced", "Crime-Scene", "Shoeprint", "Matching\",", "ECCV,", "(Sept.", "2024)", "arXiv:2404.16972", "[code]", "[data]", "Y.", "Zhao,", "H.", "Ma,", "S.", "Kong,", "C.", "Fowlke", ",", "\"In", "tance", "Tracking", "in", "3D", "Scene", "from", "Egocentric", "Video", "\",", "CVPR,", "(June", "2024)", "arXiv:2312.04117", "[pdf]", "Y.", "Dukler,", "A.", "Achille,", "H.", "Yang,", "B.", "Bowman,", "V.", "Vivek,", "L.", "Zancato,", "A.", "Ravichandran,", "C.", "Fowlke", ",", "A.", "Swaminathan,", "S.", "Soatto,", "\"Your", "repre", "entation", "are", "in", "the", "network:", "compo", "able", "and", "parallel", "adaptation", "for", "large", "cale", "model", "\",", "NeurIPS,", "(Dec.", "2023)", "[pdf]", "H.", "Li,", "C.", "Fowlke", ",", "H.", "Yang,", "O.", "Dabeer,", "Z.", "Tu,", "S.", "Soatto,", "\"Guided", "recommendation", "for", "model", "fine-tuning\",", "CVPR,", "(June", "2023)", "[pdf]", "S.", "Shafique,", "B.", "Kong,", "S.", "Kong,", "C.", "Fowlke", ",", "\"Creating", "a", "Foren", "ic", "Databa", "e", "of", "Shoeprint", "from", "Online", "Shoe", "Tread", "Photo", "\",", "WACV", "(Jan.", "2023)", "arXiv:2205.02361", "Y.", "Zhao,", "C.", "Barne", ",", "Y.", "Zhou,", "E.", "Shechtman,", "S.", "Amirghod", "i,", "C.", "Fowlke", ",", "\"GeoFill:", "Reference-Ba", "ed", "Image", "Inpainting", "of", "Scene", "with", "Better", "Geometric", "Under", "tanding\",", "WACV", "(Jan.", "2023)", "arXiv:2201.08131", "M.", "Wallingford,", "H.", "Li,", "A.", "Achille,", "A.", "Ravichandran,", "C.", "Fowlke", ",", "R.", "Bhotika,", "S.", "Soatto,", "\"Ta", "k", "Adaptive", "Parameter", "Sharing", "for", "Multi-Ta", "k", "Learning\",", "CVPR,", "(June", "2022),", "arXiv:2203.16708", "C.", "Zhu,", "P.", "Rajendran,", "P.", "Hanna,", "I.", "Efimov,", "G.", "Salama,", "C.", "Fowlke", ",", "K.", "Shivkumar,", "\"High", "re", "olution", "tructure-function", "mapping", "of", "intact", "heart", "reveal", "altered", "ympathetic", "control", "of", "infarct", "border", "zone", "\",", "JCI", "In", "ight,", "(2022),", "7(3):e153913.", "10.1172/jci.in", "ight.153913", "Z.", "Li,", "A.", "Ravichandran,", "C.", "Fowlke", ",", "M.", "Polito,", "R.", "Bhotika,", "S.", "Soatto", "\"Repre", "entation", "Con", "olidation", "for", "Training", "Expert", "Student", "\",", "Technical", "Report", "(July", "2021),", "arXiv:2107.08039", "Y.", "Zhao,", "S.", "Kong,", "C.", "Fowlke", ",", "\"Camera", "Po", "e", "Matter", ":", "Improving", "Depth", "Prediction", "by", "Mitigating", "Po", "e", "Di", "tribution", "Bia", "\",", "CVPR", ",", "(June", "2021)", "arXiv:2007.03887", "Z.", "Cai,", "A.", "Ravichandran,", "S.", "Maji,", "C.", "Fowlke", ",", "Z.", "Tu,", "S.", "Soatto", "\"Exponential", "Moving", "Average", "Normalization", "for", "Self-", "upervi", "ed", "and", "Semi-", "upervi", "ed", "Learning\",", "CVPR", ",", "(June", "2021)", "arXiv:2101.08482", "I.", "Romero,", "S.", "Kong,", "C.", "Fowlke", ",", "C.", "Jaramillo,", "M.", "Urban,", "F.", "Oboh-Ikuenobe,", "C.", "D'Apolito,", "S.", "Punya", "ena,", "\"Improving", "the", "taxonomy", "of", "fo", "il", "pollen", "u", "ing", "convolutional", "neural", "network", "and", "uperre", "olution", "micro", "copy\",", "Proc.", "of", "the", "National", "Academy", "of", "Science", "(PNAS)", "Oct", "2020,", "202007324.", "DOI:10.1073/pna", ".2007324117", "Y.", "Zhao,", "S.", "Kong,", "D.", "Shin,", "C.", "Fowlke", ",", "\"Domain", "Decluttering:", "Simplifying", "Image", "to", "Mitigate", "Synthetic-Real", "Domain", "Shift", "and", "Improve", "Depth", "E", "timation\",", "CVPR", ",", "(June", "2020)", "[pdf]", "[project]", "arXiv:2002.12114", "C.", "Huh,", "K.", "Abdelaal,", "K.", "Salina", ",", "D.", "Gu,", "J.", "Zeitoun,", "D.", "Velez,", "J.", "Peach,", "C.", "Fowlke", ",", "S.", "Gandhi,", "\"Long-term", "monocular", "deprivation", "during", "juvenile", "critical", "period", "di", "rupt", "binocular", "integration", "in", "mou", "e", "vi", "ual", "thalamu", "\",", "Journal", "of", "Neuro", "cience", ",", "(Nov.", "2019)", "10.1523/JNEUROSCI.1626-19.2019", "D.", "Shin,", "Z.", "Ren,", "E.", "Sudderth,", "C.", "Fowlke", ",", "\"3D", "Scene", "Recon", "truction", "with", "Multi-layer", "Depth", "and", "Epipolar", "Tran", "former", "\",", "ICCV", "(Oct.", "2019)", "[pdf]", "[project]", "arXiv:1902.06729", "A.", "Achille,", "M.", "Lam,", "R.", "Tewari,", "A.", "Ravichandran,", "S.", "Maji,", "C.", "Fowlke", ",", "S.", "Soatto,", "P.", "Perona,", "\"Ta", "k2Vec:", "Ta", "k", "Embedding", "for", "Meta-Learning\",", "ICCV", "(Oct.", "2019)", "[pdf]", "arXiv:1902.03545", "Z.", "Wang,", "L.", "Chen,", "S.", "Rathore,", "D.", "Shin,", "C.", "Fowlke", ",", "\"Geometric", "Po", "e", "Affordance", ":", "3D", "Human", "Po", "e", "with", "Scene", "Con", "traint", "\",", "(May", "2019).", "arXiv:1905.07718", "full", "li", "t", "of", "publication", "here...", "tudent", ":", "current", "academic", "advi", "ee", "and", "lab", "member", "Daeyun", "Shin", "(PhD)", "pa", "t", "academic", "advi", "ee", "Samia", "Shafique", "(PhD,", "2024)", "now", "at", "Google", "Yunhan", "Zhao", "(PhD,", "2024)", "now", "at", "Google", "Viktor", "Liviniuk", "(MS,", "2022)", "now", "at", "Nuro", "Alina", "Liviniuk", "(MS,", "2022)", "now", "at", "Pintere", "t", "Zhe", "Wang", "(PhD,", "2021)", "now", "at", "Crui", "e", "Chinmayee", "Athalye", "(MS,", "2020)", "Linfeng", "Wang", "(MS,", "2020)", "Shaurya", "Rathore", "(MS,", "2020)", "Ryan", "Sivoraphonh", "(BS,", "2020)", "Shu", "Kong", "(PhD,", "2019)", "now", "faculty", "at", "Univer", "ity", "of", "Macau.", "Minhaeng", "Lee", "(PhD,", "2019)", "now", "at", "Apple", "Liyan", "Chen", "(BS,", "2019)", "now", "at", "UT", "Au", "tin", "Bailey", "Kong", "(PhD,", "2018)", "Phuc", "Nguyen", "(PhD,", "2018)", "now", "at", "Google", "Dongxu", "Zhao", "(MS", "2018)", "now", "at", "UNC", "Chapel", "Hill", "Ja", "mine", "Bhanu", "hali", "(MS,", "2018)", "now", "at", "Micro", "oft", "Mahar", "hi", "Patel", "(BS,", "2017)", "now", "at", "Micro", "oft", "Golnaz", "Ghia", "i", "(PhD,", "2016)", "now", "at", "Google", "Re", "earch", "Ra\u00fal", "D\u00edaz", "(PhD,", "2016)", "now", "at", "Amazon", "Sam", "Hallman", "(PhD,", "2015)", "now", "at", "Amazon", "Gio", "Borje", "(BS,", "2015)", "now", "at", "LinkedIn", "Samreen", "Anjum", "(MS,", "2014)", "now", "at", "Qatar", "Computing", "Re", "earch", "In", "titute", "Shaofei", "Wang", "(MS,", "2013)", "now", "at", "U", "Penn", "Ja", "on", "Lee", "(BS,", "2013)", "now", "at", "OCLARO", "Julian", "Yarkony", "(PhD,2012)", "now", "at", "Experian", "Data", "Lab", "Matthew", "Nea", "e", "(BS,", "2012)", "now", "at", "Edmund", "Shu-Chi", "H", "u", "(MS,", "2012)", "Ragib", "Mor", "hed", "(MS,", "2011)", "now", "at", "Amazon", "Nityananda", "Jayadevapraka", "h", "(MS,", "2010)", "now", "at", "Apple", "Sangeeta", "Jha", "(MS,", "2010)", "now", "at", "Intel", "Tony", "Tran", "(MS,", "2009)", "now", "at", "Uber", "Denni", "Park", "(MS,", "2009)", "now", "at", "Vicariou", "pa", "t", "co-advi", "ee", "and", "vi", "itor", "Michelle", "Ngo", "(MCBS", "rotation,", "2018)", "Katiana", "Khouri", "(MCBS", "rotation,", "2017)", "Yoon", "Jung", "(BS,", "2017)", "Michael", "Chiang", "(PhD", "w/Olivier", "Cinquin,", "2015)", "Jo", "eph", "Na", "h", "(CCBS", "rotation,", "2015)", "Hyeoungho", "Bae", "(PhD", "w/Pai", "Chu,", "2013)", "now", "at", "Micro", "oft", "Yihang", "Bo", "(vi", "iting", "PhD,", "2010-2011)", "now", "at", "Beijing", "Film", "Academy", "award", ":", "UCI", "Chancellor", "fellow", "(2019-2022)", "American", "Stai", "tical", "Society", "SPAIG", "award", "for", "building", "a", "tati", "tically", "ound", "and", "cientifically", "olid", "foundation", "for", "the", "analy", "i", "and", "interpretation", "of", "foren", "ic", "evidence.", "Helmholtz", "Prize", "in", "2015", "for", "ignificant", "impact", "in", "computer", "vi", "ion", "with", "our", "paper:", "\"A", "Databa", "e"], "content_hash": "8573b5bf4fa1d0485e4ce7ff7bc08bdd"}