{"url": "http://fr.ics.uci.edu/haiti", "word_count": 371, "words": ["Family", "Reunification", "for", "Haiti", "Earthquake", "FAMILY", "REUNIFICATION", "FOR", "HAITI", "EARTHQUAKE", "Search", "Interface", "Search", "interface", "for", "the", "Per", "on", "Finder:", "Haiti", "Earthquake", "web", "ite:", "Search", "Page", "Interactive", "and", "error-tolerant", "earch", "page;", "Search", "Widget", "Interactive", "and", "error-tolerant", "earch", "widget", "that", "can", "be", "embedded", "into", "any", "web", "ite.", "Interactive", "and", "error-tolerant", "earch", "widget", "for", "the", "Red", "Cro", "FamilyLink", "web", "ite.", "Interactive", "and", "error-tolerant", "earch", "engine", "for", "over", "40,000", "mi", "ing", "per", "on", "record", "crawled", "from", "Red", "Cro", ",", "CNN", "iReport", "and", "other", "web", "ite", ".", "Data", "(January", "2010)", "CNN", "iReport", "HTML", "page", ":", "www.ireport.com.tgz", "(7,861", "file", ")", "SQL", "dump:", "2010-01-19:", "IREPORT_PERSON_88131.", "ql.gz", "(604", "new", "record", ")", "2010-01-18:", "IREPORT_PERSON_86188.", "ql.gz", "(952", "new", "record", ")", "2010-01-17:", "IREPORT_PERSON_83755.", "ql.gz", "(659", "new", "record", ")", "2010-01-16:", "IREPORT_PERSON_64235.", "ql.gz", "(5,645", "record", ")", "Family", "Link", "International", "Committee", "of", "the", "Red", "Cro", "New", "Schemata", "SQL", "dump", "(1", "table,", "denormalized):", "2010-02-28:", "ICRC_FAMILYLINKS_2010-02-08_13-55-29.", "ql.gz", "(28,034", "record", ")", "SQL", "dump", "(2", "table", ",", "normalized):", "2010-02-28:", "ICRC_PEOPLE_2010-02-08_13-55-54.", "ql.gz", "(27,401", "record", ")", "2010-02-28:", "ICRC_SEEKER_2010-02-08_13-55-54.", "ql.gz", "(28,034", "record", ")", "Layout", "after", "Jan", "20", "SQL", "dump:", "2010-01-21:", "ICRC_FAMILYLINKS_20100121.", "ql.gz", "(23,813", "record", ")", "Layout", "before", "Jan", "20", "HTML", "page", ":", "www.familylink", ".icrc.org.tgz", "(23,840", "file", ")", "SQL", "dump:", "2010-01-19:", "ICRC_PERSON_88131.", "ql.gz", "(489", "new", "record", ")", "2010-01-18:", "ICRC_PERSON_86188.", "ql.gz", "(1,034", "new", "record", ")", "2010-01-17:", "ICRC_PERSON_83755.", "ql.gz", "(1,127", "new", "record", ")", "2010-01-16:", "ICRC_PERSON_64235.", "ql.gz", "(21,188", "record", ")", "CBC", "New", "SQL", "dump:", "2010-01-18:", "CBC_PERSON_86188.", "ql.gz", "(285", "record", ")", "Konek", "yon.com", "HTML", "page", ":", "www.konek", "yon.com.tgz", "(4,571", "page", ")", "SQL", "dump:", "2010-01-22:", "KONEKSYON_PERSON_64235.", "ql.gz", "(4,571", "record", ")", "Knexu", "Forum", "Po", "t", "HTML", "page", ":", "www.knexu.org.tgz", "(817", "file", ")", "SQL", "dump:", "2010-01-19:", "KNEXU_PERSON_88131.", "ql.gz", "(816", "record", ")", "People", "Chen", "Li", "(Faculty)", "Sattam", "Al", "ubaiee", "(Student)", "Alexander", "Behm", "(Student)", "Inci", "Cetindil", "(icetindil", "..AT..", "gmail.com)", "(Student)", "Shengyue", "Ji", "(Student)", "Du", "tin", "Lakin", "(du", "tin.lakin", "..AT..", "gmail.com)", "(Student)", "Rare", "Vernica", "(Student)", "Web", "ite", "powered", "by", "our", "earch", "interface", "Haiti", "Earthquake", "and", "Recovery", "-", "Miami", "Herald", "In", "the", "new", "Helping", "Haitian", "find", "family", ",", "February", "8,", "2010", "-", "Univer", "ity", "of", "California,", "Irvine", "Search", "Engine", "Developed", "to", "Help", "Haiti", "Victim", ",", "January", "27,", "2010", "-", "Donald", "Bren", "School", "of", "Information", "and", "Computer", "Science", ",", "Univer", "ity", "of", "California,", "Irvine", "UCI", "aid", "hunt", "for", "mi", "ing", "Haitian", ",", "January", "16,", "2010", "-", "The", "Orange", "County", "Regi", "ter", "\u00ab", "Back", "to", "homepage"], "content_hash": "7a4665ae86a25cd133a70da3fd7de0a1"}