{"url": "https://www.stat.uci.edu/professors-berrocal-and-shahbaba-named-american-statistical-association-fellows", "word_count": 613, "words": ["Profe", "or", "Berrocal", "and", "Shahbaba", "Named", "American", "Stati", "tical", "A", "ociation", "Fellow", "Two", "faculty", "member", "from", "UCI\u2019", "Donald", "Bren", "School", "of", "Information", "and", "Computer", "Science", "(", "ICS", ")", "were", "recently", "named", "fellow", "of", "the", "American", "Stati", "tical", "A", "ociation", "(", "ASA", "):", "Veronica", "Berrocal", "and", "Babak", "Shahbaba", ".", "A", "ociate", "Profe", "or", "Berrocal", "received", "the", "honor", "for", "\u201cre", "earch", "in", "patial", "and", "patio-temporal", "tati", "tic", "and", "application", "to", "atmo", "pheric", "and", "environmental", "cience", "and", "environmental", "epidemiology;", "and", "for", "ub", "tantial", "ervice", "to", "the", "profe", "ion.\u201d", "She", "work", "to", "develop", "tati", "tical", "model", "that", "can", "de", "cribe", "the", "interdependence", "and", "correlation", "among", "ob", "ervation", ",", "and", "explore", "how", "that", "dependence", "varie", "in", "pace", "and", "time.", "The", "e", "model", "help", "an", "wer", "que", "tion", "uch", "a", ":", "\u201cWhat", "are", "the", "e", "timated", "level", "of", "air", "pollution", "at", "location", "without", "monitor", "?\u201d", "or", "\u201cHow", "doe", "poverty", "in", "certain", "neighborhood", "change", "over", "time?\u201d", "\u201cI", "am", "very", "thankful", "to", "Bri", "a", "Sanchez", "at", "Drexel", "Univer", "ity", "who", "ubmitted", "the", "nomination,", "Michele", "Guindani", "who", "helped", "gather", "the", "letter", "of", "upport,", "and", "the", "letter", "writer", "who", "upported", "my", "nomination,\u201d", "ay", "Berrocal.", "\u201cI", "am", "grateful", "to", "the", "ASA", "Committee", "on", "Fellow", "for", "be", "towing", "uch", "an", "honor", "to", "me", "and", "providing", "me", "with", "additional", "motivation", "to", "continue", "on", "thi", "path.\u201d", "Berrocal", "ay", "he", "hare", "thi", "recognition", "with", "all", "the", "people", "who", "have", "been", "fundamental", "for", "her", "growth", "a", "a", "tati", "tician.", "\u201cMy", "Ph.D.", "and", "po", "tdoc", "advi", "er", ",", "Adrian", "Raftery", "and", "Alan", "Gelfand,", "re", "pectively,", "who", "introduced", "me", "to", "patial", "and", "environmental", "tati", "tic", "and", "taught", "me", "how", "to", "carry", "out", "tati", "tical", "re", "earch,", "have", "been", "wonderful", "mentor", "throughout", "the", "year", ".", "I", "al", "o", "want", "to", "acknowledge", "my", "colleague", "at", "the", "Univer", "ity", "of", "Michigan,", "UCI", "and", "other", "in", "titution", "who", "et", "great", "example", "for", "me", "with", "their", "impactful", "re", "earch", "and", "their", "excellence", "in", "mentoring,", "teaching", "and", "ervice.\u201d", "Profe", "or", "Shahbaba", "wa", "named", "an", "ASA", "fellow", "for", "\u201cout", "tanding", "contribution", "to", "Baye", "ian", "tati", "tic", ",", "calable", "computation", "and", "a", "wide", "range", "of", "domain", "cience", "application", ";", "and", "for", "exceptional", "profe", "ional", "ervice", "and", "leader", "hip", "on", "promoting", "data", "cience.\u201d", "Hi", "re", "earch", "focu", "e", "on", "Baye", "ian", "nonparametric", "method", "and", "hierarchical", "Baye", "ian", "model", "and", "their", "application", "in", "large-", "cale", "biological", "cience", ".", "He", "ha", "al", "o", "worked", "to", "develop", "more", "efficient", "computational", "method", "to", "facilitate", "the", "application", "of", "Baye", "ian", "tati", "tic", "to", "data-inten", "ive", "cientific", "problem", ",", "and", "he", "erve", "a", "director", "of", "UCI\u2019", "Data", "Science", "Initiative", ".", "\u201cIt", "i", "a", "great", "honor", "to", "be", "recognized", "by", "your", "peer", ".", "I\u2019m", "e", "pecially", "thankful", "to", "Annie", "Qu,", "who", "ubmitted", "the", "nomination,", "and", "We", "John", "on,", "Peter", "Mueller", "and", "Gary", "Ro", "ner,", "who", "upported", "my", "nomination,\u201d", "ay", "Shahbaba.", "\u201cI", "owe", "thi", "to", "my", "tudent", "and", "collaborator", "who", "worked", "with", "me", "over", "the", "pa", "t", "12", "year", "a", "I", "wa", "building", "my", "academic", "career.", "I", "al", "o", "owe", "it", "to", "my", "wonderful", "academic", "advi", "er", ",", "Radford", "Neal,", "Rob", "Tib", "hirani", "and", "Sylvia", "Plevriti", ",", "who", "helped", "me", "to", "get", "tarted", "in", "thi", "field.\u201d", "For", "nearly", "100", "year", ",", "the", "ASA", "ha", "been", "recognizing", "out", "tanding", "contribution", "from", "it", "member", "with", "the", "fellow", "de", "ignation.", "Berrocal", "and", "Shahbaba", "join", "the", "following", "colleague", "from", "the", "Department", "of", "Stati", "tic", "in", "receiving", "thi", "honor:", "Profe", "or", "Annie", "Qu,", "Michele", "Guindani,", "Daniel", "Gillen,", "Hal", "Stern", "and", "Bin", "Nan,", "and", "emeriti", "faculty", "Je", "ica", "Utt", "and", "We", "ley", "John", "on.", "\u2014", "Shani", "Murray", "\u00ab", "Qu", "Named", "2024", "IMS", "Medallion", "Lecturer", "Don\u2019t", "Think", "You", "Can", "Learn", "Baye", "ian", "Stati", "tic", "?", "Think", "Again", "With", "\u2018Baye", "Rule", "!\u2019", "\u00bb", "Quick", "Link", ":", "New", "Archive", "Upcoming", "Seminar", "Seminar", "Serie", "Archive", "Contact", "the", "Department"], "content_hash": "08c295102f7b7e33227c4b7016108a35"}