{"url": "https://www.stat.uci.edu/qu-named-2024-ims-medallion-lecturer", "word_count": 149, "words": ["Qu", "Named", "2024", "IMS", "Medallion", "Lecturer", "The", "In", "titute", "of", "Mathematical", "Stati", "tic", "(IMS)", "named", "Annie", "Qu,", "Chancellor\u2019", "Profe", "or", "of", "tati", "tic", ",", "a", "one", "of", "the", "2024", "IMS", "Medallion", "Award", "and", "Lecture", ".", "Each", "year,", "eight", "Medallion", "Lecturer", "are", "cho", "en", "acro", "all", "area", "of", "tati", "tic", "and", "probability", "by", "the", "IMS", "Committee", "on", "Special", "Lecture", ".", "The", "Medallion", "nomination", "i", "an", "honor", "and", "an", "acknowledgment", "of", "a", "ignificant", "re", "earch", "contribution", "to", "one", "or", "more", "re", "earch", "area", ".", "Each", "Medallion", "Awardee", "and", "Lecturer", "will", "receive", "a", "medallion", "in", "a", "ceremony", "preceding", "the", "lecture.", "Profe", "or", "Qu", "will", "deliver", "her", "Medallion", "Lecture", "at", "the", "2024", "Joint", "Stati", "tical", "Meeting", "in", "Portland,", "Oregon.", "\u00ab", "NSF", "Announce", "2022", "Graduate", "Re", "earch", "Fellow", "Profe", "or", "Berrocal", "and", "Shahbaba", "Named", "American", "Stati", "tical", "A", "ociation", "Fellow", "\u00bb", "Quick", "Link", ":", "New", "Archive", "Upcoming", "Seminar", "Seminar", "Serie", "Archive", "Contact", "the", "Department"], "content_hash": "a595b29d735f95ff5837b097cb469958"}