{"url": "https://futurehealth.ics.uci.edu/global-emerging-technologies-get-digital-health-informatics", "word_count": 1021, "words": ["UCI", "In", "titute", "for", "Future", "Health", "|", "Global", "Emerging", "Technologie", "(GET)", "Digital", "Health", "Informatic", "EVENTS", "Home", "/", "Event", "/", "Global", "Emerging", "Technologie", "(GET)...", "A", "Work", "hop", "on:", "Global", "Emerging", "Technologie", "(GET)", "Digital", "Health", "Informatic", "IFH", "wa", "co-ho", "ted", "the", "GET", "Digital", "Health", "Informatic", "Forum", "(ISO/TC215", "+", "IEEE-SA", "+", "HL7", "International)", "at", "UC", "Irvine", "on", "November", "6", "and", "November", "7,", "2024.", "International", "Digital", "Health", "Informatic", "Standard", "Expert", "(from", "all", "acro", "the", "globe:", "Canada,", "China,", "Japan,", "Korea,", "India,", "Norway,", "Spain,", "UK", "&", "US)", "are", "a", "embling", "along", "with", "indu", "try,", "academia", "&", "government", "entitie", "to", "pre", "ent,", "di", "cu", "&", "deliberate", "about", "global", "emerging", "technologie", "for", "digital", "health", "and", "how", "tandard", ",", "informatic", "and", "technology", "i", "haping", "our", "live", "in", "the", "21", "t", "century!", "Focu", ":", "Key", "focu", "area", "include", "per", "onalized", "health", "navigation,", "food", "computing", "&", "A2L:", "Ageing,", "Longevity", "&", "Life", "tyle.", "Agenda:", "Nov", "6,", "2024", "@", "ISEB#1010", "Interdi", "ciplinary", "Science", "and", "Engineering", "Building", "(419", "Phy", "ical", "Science", "Quad,", "Irvine,", "CA", "92697)", "The", "Digital", "Health", "Informatic", "Forum", "bring", "together", "international", "tandard", "expert", "from", "over", "10", "countrie", "and", "US", "ba", "ed", "expert", "from", "the", "indu", "try,", "academia", "and", "government.", "Thi", "i", "a", "unique", "opportunity", "to", "li", "ten,", "learn,", "collaborate", "and", "network", "among", "t", "the", "e", "global", "leader", ".", "Today\u2019", "focu", "i", "on", "ome", "of", "the", "activitie", "of", "ISO/TC215", "Work", "Group#11:", "Per", "onalized", "Digital", "Health", "(PDH)", ":", "Per", "onal", "Health", "Navigation", "(PHN)", "and", "Food", "&", "Nutrition", "(F&N)", "and", "how", "informatic", "i", "playing", "a", "crucial", "role", "in", "haping", "our", "health", "in", "the", "21", "t", "century!", "Morning", "e", "ion", "PHN:", "Per", "onal", "Health", "Navigator", "ROLE", "NAME", "8:30am", "\u2013", "8:49am", "Regi", "tration", "&", "Coffee", "8:50am", "\u2013", "8:59am", "Introducing", "GET", "DHI", "FORUM", "Vote", "of", "Thank", "Chairman", "IEEE", "Southern", "California", "Gora", "Datta,", "FHL7", "9:00am", "\u2013", "9:15am", "Welcome", "addre", "Chairman", "ISO/TC215", "Todd", "Cooper", "9:15am", "\u2013", "10:00am", "Day#1", "Opening", "Keynote", "Vice", "Chancellor", "for", "Re", "earch", "at", "Univer", "ity", "of", "California", "(UCI)", "Irvine", "&", "Prof", "of", "EE&CS", "Dr", "Pramod", "Khargonekar", "10:00am", "\u2013", "10:30am", "Se", "ion", "Keynote:", "Per", "onal", "Health", "Navigation", "(PHN)", "Director,", "In", "titute", "of", "Future", "Health,", "UCI", "Dr", "Rame", "h", "Jain", "10:30am", "\u2013", "11:00am", "BREAK", "Networking", "Coffee/Tea", "11:00am", "\u2013", "11:20pm", "Keynote#1:", "CHA", "A", "oc", "Director,", "IFH", "@", "UCI", "Dr", "Amir", "Rahmani", "11:20am", "\u2013", "11:40pm", "Keynote#2:", "FHIR", "Informatic", "Chief", "Standard", "Development", "Officer,", "HL7", "International", "Dr", "Dan", "Vreeman", "(remote)", "11:40am", "\u2013", "12:30pm", "Interactive", "Panel#1", "PHN", "panel", "Moderator:", "Todd", "Cooper", "12:30pm", "\u2013", "1:30pm", "LUNCH", "Networking", "Served", "on", "premi", "e", "Afternoon", "e", "ion", "Food", "&", "Nutrition", "(F&N)", "1:30pm", "\u2013", "2:15pm", "Keynote#3:", "Food", "&", "Nutrition", "A", "ociate", "Profe", "or,", "Head", "of", "the", "AI", "in", "Health", "and", "Nutrition", "Laboratory,", "Univer", "ity", "of", "Bern", "Univer", "ity", "of", "Tokyo", "Dr", "Stavroula", "G.", "Mougiakakou", "Dr", "Yoko", "Yamakata", "(remote)", "2:15pm", "\u2013", "3:00pm", "Interactive", "Panel#2", "F&N", "panel", "Moderator:", "Rame", "h", "Jain,", "PhD", "3:00pm", "\u2013", "3:30pm", "BREAK", "Networking", "Coffee/Tea", "3:30pm", "\u2013", "4:00pm", "Keynote#4:", "Impact", "of", "AI", "\u2013", "Conver", "ational", "Health", "Agent", "A", "i", "tant", "Director,", "UCI-In", "titute", "for", "Future", "Health", "Iman", "Azimi,", "PhD", "4:00pm", "\u2013", "4:30pm", "Keynote#5:", "Impact", "of", "Emerging", "Technologie", "on", "Digital", "Health", "HL7", "Board", "Director-Elect", "Vice", "Chair", "IEEE", "Blockchain", "TC", "ISO/TC215", "Convenor", "WG#10", "Gora", "Datta,", "FHL7", "4:30pm", "\u2013", "5:00pm", "Keynote#6:", "Future", "Collaboration", "Vital\u2019Nomic", "Initiative", "(VINI)", "Executive", "Director", "Brian", "Hagerty", "5:00pm", "\u2013", "6:00pm", "EVENING", "RECEPTION", "&", "NETWORKING", "Nov", "7,", "2024", "@", "DBH#4100", "Don", "Bren", "Hall", "(3054", "Donald", "Bren", "Hall", "Irvine,", "CA", "92697-3435)", "The", "focu", "of", "today\u2019", "Forum", "i", "to", "gain", "per", "pective", "on", "current", "re", "earch", "and", "project", "in", "the", "area", "of", "Aging,", "Longevity", "&", "Life", "tyle", "(A2L)", ",", "followed", "by", "an", "open", "di", "cu", "ion", "of", "how", "the", "international", "community", "might", "collaborate", "to", "create", "tandard", "and", "other", "tool", "to", "facilitate", "communitie", "\u2019", "effort", "to", "create", "environment", "that", "upport", "the", "le", "on", "learned", "a", "well", "a", "continued", "re", "earch.", "The", "objective", "i", "to", "identify", "both", "a", "vi", "ion", "for", "thi", "work", "within", "ISO/TC", "215", "and", "the", "broader", "tandard", "community", "and", "capture", "the", "re", "ult", "of", "thi", "work", "hop", "and", "lay", "out", "a", "trategy", "for", "advancing", "international", "tandardization.", "8:30am", "\u2013", "8:59am", "Regi", "tration", "&", "Coffee", "9:00am", "\u2013", "9:10am", "Introduction", "Day#2", "Chairman", "IEEE", "Southern", "California", "Gora", "Datta,", "FHL7", "Morning", "e", "ion", "A2L:", "Aging,", "Longevity", "&", "Life", "tyle", "9:10am", "\u2013", "9:15am", "Introducing", "Morning", "Se", "ion", "A2L:", "Aging,", "Longevity", "&", "Life", "tyle", "Todd", "Cooper", "9:15am", "\u2013", "10:15am", "DAY#2:", "Opening", "Keynote:", "A2L", "Di", "tingui", "hed", "Profe", "or,", "School", "of", "Medicine,", "Loma", "Linda", "Univer", "ity", "Dr", "Gary", "Fra", "er", "10:15am", "\u2013", "10::30am", "Briefing", "on", "ISO/TC215", "WG11", "and", "in", "particular,", "the", "A2L", "Initiative", "Convenor,", "ISO/TC215-WG11", "Per", "onalized", "Digital", "Health", "Fr\u00e9d\u00e9ric", "Laroche", "10:30am", "\u2013", "11:00am", "BREAK", "Networking", "Coffee/Tea", "11:00am", "\u2013", "11:30am", "Global", "Informatic", "Keynote", "CEO", "HL7", "International", "Dr", "Charle", "Jaffe,", "MD", "11:30am", "\u2013", "12:30pm", "A2L:", "Work", "hop", "exploring", "the", "po", "ible", "role", "of", "international", "health", "informatic", "tandard", "to", "advance", "the", "learning", "of", "A2L", "re", "earch", "into", "the", "daily", "life", "of", "individual", "&", "communitie", "Secretary,", "ISO/TC215-WG11", "Per", "onalized", "Digital", "Health", "Moderator:", "Daniel", "Berezeanu", "Dr", "Gary", "Fra", "er", "Dr", "Chuck", "Jaffe", "Todd", "Cooper", "12:30pm", "\u2013", "1:30pm", "LUNCH", "Networking", "Afternoon", "e", "ion", "Real-World-Experience", "1:30pm", "\u2013", "2:00pm", "Keynote#7:", "Impact", "of", "Air", "Quality", "on", "Health", "Air", "Re", "ource", "Engineer,", "California", "Environmental", "Protection", "Agency", "(Cal-EPA)", "Dr", "Sulekha", "Chattopadhyay", "2:00pm", "\u2013", "2:30pm", "Phy", "ician", "Panel:", "Practicing", "Phy", "ician", "&", "Remote", "Patient", "Monitoring", "(RPM)", "to", "Care", "Dr", "Je", "ica", "Ba", "a,", "Family", "Medicine", "Dr", "Mehul", "Sonawala,", "Internal", "Medicine", "Dr", "Kamiar", "Alaei,", "Infectiou", "Di", "ea", "e", "Speciali", "t", "Dr", "Narendra", "Par", "on", "2:30pm", "\u2013", "3:00pm", "Keynote#8:", "IEEE-SA", "HLS", "enable", "Digital", "Innovation", "IEEE-SA", "Health", "&", "Life", "Science", "(HLS)", "Global", "Practice", "Leader", "Maria", "Palombini", "3:00pm", "\u2013", "3:30pm", "BREAK", "Networking", "Coffee/Tea", "3:30pm", "\u2013", "4:15pm", "Keynote#9:", "AI", "for", "Re", "earch", "&", "Development", "(AI4R&D)", "Technology", "Subject", "Matter", "Expert,", "IEEE", "Orange", "County", "Ha", "Patel", "(ex-Bell", "Lab", ")", "4:15pm", "\u2013", "5:00pm", "Panel:", "Future", "of", "Health-Tech", "Workforce", ":", "CCPHIT", "a", "ca", "e", "tudy", "Chair", "Department", "of", "Health", "Science", ",", "California", "State", "Univer", "ity", "Long", "Beach", "CCPHIT", "Project", "Coordinator,", "PHIT", "Faculty", "CSU", "Long", "Beach", "Dr", "Kamiar", "Alaei", "Dr", "Brian", "Kwan", "5:00pm", "\u2013", "6:00pm", "EVENING", "RECEPTION", "&", "NETWORKING", "Regi", "ter", "here:", "http", "://event", ".vtool", ".ieee.org/m/443377", "Location:", "UC", "Irvine", "Date:", "November", "6-7,", "2024", "Time:", "08:30", "-", "18:00", "(Pacific", "Time)", "New", "Event", "Project", "IFH", "Member", "About", "IFH", "Key", "di", "cipline"], "content_hash": "8c76c02af6c6fbd1329ee33263059c72"}