{"url": "https://grape.ics.uci.edu/wiki/public/wiki/cs122b-2018-winter?version=77", "word_count": 1945, "words": ["c", "122b-2018-winter", "\u2013", "Public", "Login", "Preference", "About", "Trac", "Regi", "ter", "wiki:", "c", "122b-2018-winter", "Context", "Navigation", "\u2190", "Previou", "Ver", "ion", "View", "Late", "t", "Ver", "ion", "Next", "Ver", "ion", "\u2192", "Ver", "ion", "77", "(modified", "by", "chenli", ",", "8", "year", "ago", ")", "(", "diff", ")", "--", "CS122B", "Spring", "2018:", "Project", "in", "Databa", "e", "and", "Web", "Application", "Syllabu", "Online", "Di", "cu", "ion", "Project", "(Subject", "to", "change)", "Quizze", "Cour", "e", "Information", "Overview", "Difference", "from", "Earlier", "Offering", "U", "ing", "Cloud", "Service", "Prerequi", "ite", "Grading", "Breakdown", "Textbook", "U", "ing", "Other", "Domain", "U", "ing", "Github", "Working", "in", "Group", "Award", "Project", "Late", "Policy", "Policy", "on", "Academic", "Hone", "ty", "Project", "Overview", "CS122B", "Spring", "2018:", "Project", "in", "Databa", "e", "and", "Web", "Application", "Time:", "T/Th", "2:00", "pm", "\u2013", "3:20", "pm", "(Check", "the", "\u200b", "UCI", "Calendar", "for", "holiday", "information)", "Location:", "\u200b", "SSLH", "100", ".", "Name", "Office", "Hour", "Place", "Email", "In", "tructor:", "\u200b", "Chen", "Li", "Tue", "day", ",", "12:45", "pm", "-", "1:45", "pm", "DBH", "2092", "chenli", "AT", "ic", ".uci.edu", "A", "i", "tant:", "Avina", "h", "Kumar", "Wedne", "day", "1:15pm", "-", "2:15pm", "ICS", "464C", "avina", "k1", "AT", "uci.edu", "A", "i", "tnat:", "Qiu", "hi", "Bai", "Friday", "9:30am", "-", "10:30am", "ICS", "464C", "qbai1", "AT", "uci.edu", "A", "i", "tant:", "Zuozhi", "Wang", "Monday", "4pm", "-", "5pm,", "Thur", "day", "4pm", "-", "5pm", "ICS", "464C", "zuozhiw", "AT", "uci.edu", "Syllabu", "No.", "Date", "Note", "01", "01/09/18,", "Tu", "Introduction", "\u200b", ",", "Cour", "e", "Overview,", "MySQL,", "JDBC,", "AWS,", "Setup", "Script", "\u200b", "02", "01/11/18,", "Th", "Git", "Overview", "\u200b", "U", "ing", "Github", "in", "CS122B", ",", "Sample", "JDBC", "Program", "03", "01/16/18,", "Tu", "\u200b", "In", "tall", "Tomcat", ",", "TomcatTe", "t", "Example", ",", "\u200b", "MySQL", "Logging", ",", "\u200b", "Tomcat", "Logging", ",", "ODBC", "\u200b", "04", "01/18/18,", "Th", "Project", "1", "Development,", "Project", "2", "Overview", ",", "Form", "Example", ",", "\u200b", "\"Cookie", "Idea\"", "in", "Movie", "Memento", "05", "01/23/18,", "Tu", "Servlet", "Se", "ion", "Example", ",", "Shopping", "cart,", "\u200b", "Pagination", "\u200b", "06", "01/25/18,", "Th", "Searching/Brow", "ing", "\u200b", ",", "JSP", ",", "\u200b", "ASP", ",", "\u200b", "Setup", "Maven", "07", "01/30/18,", "Tu", "Frontend/Backend", "Seperation", "08", "02/01/18,", "Th", "Web", "architecture", "\u200b", ",", "Quiz", "1", "09", "02/06/18,", "Tu", "Remote", "Acce", "to", "AWS", "MySQL", "\u200b", ",", "Domain", "regi", "tration", "\u200b", ",", "reCaptcha", "(", "PPT", "\u200b", ")", "10", "02/07/18,", "Th", "HTTPS", ",", "Stored", "Procedure", "\u200b", "11", "02/13/18,", "Tu", "XML", "\u200b", "12", "02/15/18,", "Th", "Sample", "Employee", "XML", "File", "\u200b", ",", "SAX", "Par", "er", "\u200b", ",", "Employee.java", "\u200b", ",", "DOM", "Par", "er", "\u200b", ",", "\u200b", "AutoCommit", ",", "Batch", "In", "ert", "\u200b", ",", "\u200b", "Load", "data", "file", "Online", "Di", "cu", "ion", "Piazza", ":", "\u200b", "http://piazza.com/uci/winter2018/c", "122b", "Project", "(Subject", "to", "change)", "Project", "Topic", "Day", "Due", "Date", "Grading", "Rubric", "Project", "1", "MySQL", "creation,", "JDBC,", "Tomcat,", "AWS", "14", "day", "Week", "3", "Monday,", "Jan.", "22", "\u200b", "P1", "Project", "2", "Developing", "Fablix", "Web", "ite", "\u200b", "An", "earlier", "demo", "18", "day", "Week", "5", "Friday,", "Feb.", "9", "\u200b", "P2", "Project", "3", "reCaptcha,", "HTTPS,", "Stored", "Procedure,", "XML", "Par", "ing", "12", "day", "Week", "7", "Thur", "day,", "Feb.", "22", "Project", "4", "Ajax,", "Search,", "UDF,", "and", "Android", "14", "day", "Week", "9", "Wedne", "day,", "Mar.", "8", "Project", "5", "Scaling", "Fabflix", "9", "day", "Week", "10", "Friday,", "Mar.", "16", "\u200b", "Github", "U", "ername", "\u200b", "Looking", "for", "Teammate", "\u200b", "Team", "Signup", "Sheet", "\u200b", "Project", "1Demo", "Signup", "Sheet", "\u200b", "Project", "2", "Demo", "Signup", "Sheet", "Quizze", "Quiz", "1:", "02/01/18,", "Th", "Quiz", "2:", "TBD", "Quiz", "3:", "TBD", "Cour", "e", "Information", "Overview", "Thi", "cour", "e", "expo", "e", "tudent", "to", "advanced", "programming", "concept", "and", "provide", "tudent", "with", "a", "greater", "focu", "on", "u", "ing", "DBMS", "technique", "to", "build", "Web-ba", "ed", "application", ".", "It", "i", "intended", "for", "two", "purpo", "e", ":", "(1)", "It", "introduce", "tudent", "to", "the", "modern", "data", "management", "technique", "including", "databa", "e", "connectivity,", "Web", "application", "development,", "extending", "databa", "e", "function", ",", "databa", "e", "admini", "tration,", "and", "XML.", "(2)", "It", "teache", "tudent", "how", "to", "u", "e", "the", "e", "technologie", "to", "build", "real-world", "application", ".", "The", "cour", "e", "build", "on", "\u200b", "CS122A", ",", "which", "introduce", "tudent", "to", "the", "cla", "ical", "relational", "databa", "e", "and", "SQL", "programming.", "Difference", "from", "Earlier", "Offering", "Compared", "to", "previou", "offering", ",", "we", "are", "going", "to", "make", "a", "few", "change", "thi", "quarter,", "including", "u", "ing", "Github.", "U", "ing", "Cloud", "Service", "We", "will", "heavily", "u", "e", "cloud", "ervice", "(Amazon", "AWS", "and", "Google", "Cloud", "Platform)", "in", "the", "cour", "e.", "You", "are", "expected", "to", "launch", "in", "tance", "on", "AWS", "to", "deploy", "ome", "of", "the", "project", "you", "are", "developing.", "AWS", "provide", "free-tier", "64-bit", "Ubuntu", "in", "tance", "!", "In", "addition,", "you", "are", "welcome", "to", "participate", "in", "the", "\u200b", "AWS", "Educate", "program,", "which", "can", "provide", "$100", "AWS", "credit", "per", "tudent.", "We", "will", "provide", "more", "in", "truction", "about", "how", "to", "u", "e", "their", "ervice", "to", "deploy", "your", "project", ".", "We", "will", "al", "o", "u", "e", "Google", "Cloud", "Platform", "(GCP)", "a", "well,", "which", "provide", "$300", "free", "trial", "credit", "at", "\u200b", "Google", "Cloud", "Free", "Trial", ".", "Prerequi", "ite", "You", "hould", "have", "taken", "CS122A", "or", "an", "equivalent", "cour", "e.", "In", "addition,", "you", "hould", "have", "a", "rea", "onable", "under", "tanding", "of", "core", "computer", "cience", "concept", ",", "good", "familiarity", "with", "relational", "databa", "e", "(equivalent", "of", "CS122A),", "good", "programming", "kill", "in", "Java,", "kill", "to", "learn", "other", "programming", "language", ",", "and", "familiarity", "with", "ba", "ic", "undergraduate-level", "operating", "y", "tem", "concept", ".", "Above", "all,", "you", "need", "to", "have", "a", "po", "itive", "attitude", "toward", "learning,", "no", "inhibition", "about", "working", "in", "group", "and", "learning", "from", "each", "other.", "If", "you", "are", "not", "ure", "whether", "you", "meet", "requirement", ",", "do", "talk", "to", "the", "in", "tructor", "after", "the", "fir", "t", "lecture", "to", "make", "ure", "you", "are", "ready", "to", "take", "thi", "cour", "e.", "Grading", "Breakdown", "Project", ":", "88%", "In-cla", "Quizze", ":", "11%", "Participation", "in", "EEE", "Cla", "Evaluation:", "1%", "For", "all", "the", "graded", "project", "and", "exam", ",", "if", "you", "di", "agree", "with", "the", "grading,", "you", "can", "di", "cu", "with", "u", "within", "two", "week", "after", "they", "are", "returned.", "After", "that,", "all", "the", "grade", "will", "be", "finalized.", "For", "each", "project", "demo,", "we", "a", "ume", "each", "group", "can", "provide", "their", "own", "computing", "environment", "(either", "a", "laptop", "or", "a", "remote", "de", "ktop)", "to", "how", "the", "demo.", "If", "you", "cannot", "provide", "uch", "an", "environment,", "plea", "e", "let", "u", "know", "before", "the", "demo,", "o", "that", "we", "can", "find", "a", "olution.", "Textbook", "Many", "online", "tutorial", ".", "U", "ing", "Other", "Domain", "Our", "main", "project", "are", "u", "ing", "the", "movie", "domain,", "with", "provided", "chema", ",", "data,", "and"], "content_hash": "744143e6ec0ccd1f536540ef3cfdde1a"}