{"url": "https://acoi.ics.uci.edu/seminar-series", "word_count": 1894, "words": ["Seminar", "Serie", "\u2013", "ACO", "Center", "@", "UCI", "Join", "U", "When:", "Thur", "day", "at", "4pm", "(unle", "otherwi", "e", "noted)", "Where:", "Donald", "Bren", "Hall,", "room", "4011", "(unle", "otherwi", "e", "noted)", "Talk", "will", "be", "followed", "by", "Coffee", "&", "Refre", "hment", "Winter", "2024", "January", "18,", "2024", "\u2013", "2:00", "pm", "in", "DBH", "3011", "Binghui", "Peng", "(Columbia", "Univer", "ity)", "Fa", "t", "wap", "regret", "minimization", "and", "application", "to", "approximate", "correlated", "equilibria", "January", "25,", "2024", "\u2013", "2:00", "pm", "in", "DBH", "3011", "Thanh", "Nguyen", "(Purdue", "Univer", "ity)", "Market", "de", "ign", "problem", ":", "Competitive", "equilibrium", "and", "table", "allocation", "February", "1,", "2024", "\u2013", "2:00", "pm", "in", "DBH", "3011", "Thoma", "Rothvo", "(Univer", "ity", "of", "Wa", "hington)", "The", "Sub", "pace", "Flatne", "Conjecture", "and", "Fa", "ter", "Integer", "Programming", "February", "8,", "2024", "\u2013", "2:00", "pm", "in", "DBH", "3011", "Kevin", "Leyton-Brown", "(Univer", "ity", "of", "Briti", "h", "Columbia)", "AI-Enabled", "Market", "De", "ign:", "Le", "on", "Learned", "from", "Radio", "Spectrum", "Reallocation", "Fall", "2023", "November", "15,", "2023", "\u2013", "4:00", "pm", "in", "DBH", "4011", "O", "ama", "A.", "Hanna", "(UCLA)", "Stocha", "tic", "Contextual", "Bandit", "Are", "Not", "Harder", "Than", "Linear", "Bandit", "November", "1,", "2023", "\u2013", "4:00", "pm", "in", "DBH", "4011", "Martin", "Bichler", "(Technical", "Univer", "ity", "of", "Munich)", "Core-", "tability", "in", "market", "with", "budget-con", "trained", "bidder", "Spring", "2023", "May", "11,", "2023", "\u2013", "4:00", "pm", "in", "DBH", "4011", "Jo", "eph", "Root", "(Univer", "ity", "of", "Chicago)", "Royal", "Proce", "ion", ":", "Incentive", ",", "Efficiency", "and", "Fairne", "in", "Two-", "ided", "Matching", "May", "4,", "2023", "\u2013", "4:00", "pm", "in", "DBH", "4011", "Noga", "Alon", "(Princeton", "Univer", "ity)", "Univer", "al", "Graph", "and", "Adjacency", "Labeling", "April", "20,", "2023", "\u2013", "4:00", "pm", "in", "DBH", "4011", "Kirill", "Rudov", "(Princeton", "Univer", "ity)", "Fragile", "Stable", "Matching", "April", "13,", "2023", "\u2013", "4:00", "pm", "in", "DBH", "4011", "Federico", "Echenique", "(UC", "Berkeley)", "Empirical", "Welfare", "Economic", "June", "15,", "2023", "\u2013", "4:00", "pm", "in", "DBH", "4011", "Vijay", "V.", "Vazirani", "(Univer", "ity", "of", "California,", "Irvine", ")", "A", "Theory", "of", "Alternating", "Path", "and", "Blo", "om", ",", "from", "the", "Per", "pective", "of", "Minimum", "Length", "Winter", "2023", "March", "16,", "2023", "\u2013", "4:00", "pm", "in", "DBH", "4011", "Michael", "O", "trov", "ky", "(Stanford", "Univer", "ity)", "Pure-Strategy", "Equilibrium", "in", "the", "Generalized", "Fir", "t-Price", "Auction", "March", "9,", "2023", "\u2013", "4:00", "pm", "in", "DBH", "4011", "Vahideh", "Man", "hadi", "(Yale", "School", "of", "Management)", "Re-de", "igning", "Recommendation", "on", "VolunteerMatch:", "Theory", "and", "Practice", "March", "2,", "2023", "\u2013", "4:00", "pm", "in", "DBH", "4011", "Nikhil", "Ban", "al", "(Univer", "ity", "of", "Michigan)", "The", "power", "of", "two", "choice", "for", "ball", "into", "bin", ":", "Beyond", "greedy", "trategie", "February", "23,", "2023", "\u2013", "4:00", "pm", "in", "DBH", "4011", "Levi", "DeValve", "(Univer", "ity", "of", "Chicago)", "Approximate", "Submodularity", "in", "Network", "De", "ign", "Problem", "February", "16,", "2023", "\u2013", "4:00", "pm", "in", "DBH", "4011", "Yannai", "Gonczarow", "ki", "(Harvard", "Univer", "ity)", "Strategyproof-Expo", "ing", "Mechani", "m", "De", "cription", "February", "9,", "2023", "\u2013", "4:00", "pm", "in", "DBH", "4011", "Shayan", "Ovei", "Gharan", "(Univer", "ity", "of", "Wa", "hington)", "The", "MCMC", "method", "and", "High", "Dimen", "ional", "Expander", "January", "19,", "2023", "\u2013", "4:00", "pm", "in", "DBH", "4011", "Martin", "Bullinger", "(TU", "Munich)", "Single-Agent", "Dynamic", "in", "Hedonic", "Game", "Fall", "2022", "November", "17,", "2022", "\u2013", "4:00", "pm", "in", "DBH", "4011", "G\u00e9rard", "Cornu\u00e9jol", "(Carnegie", "Mellon", "Univer", "ity)", "On", "packing", "dijoin", "in", "directed", "graph", "November", "10,", "2022", "\u2013", "4:00", "pm", "in", "DBH", "4011", "Olya", "Ohrimenko", "(Univer", "ity", "of", "Melbourne)", "Leakage", "and", "Protection", "of", "Data", "et", "Propertie", "November", "3,", "2022", "\u2013", "4:00", "pm", "in", "DBH", "4011", "Rad", "Niazadeh", "(Univer", "ity", "of", "Chicago", ")", "When", "Matching", "Meet", "Batching:", "Optimal", "Multi-", "tage", "Algorithm", "and", "Application", "October", "27,", "2022", "\u2013", "11:00", "am", "in", "Zoom", "\u2013", "TBA", "Fanyin", "Zheng", "(Columbia", "Bu", "ine", "School)", "Improving", "Match", "Rate", "in", "Dating", "Market", "through", "A", "ortment", "Optimization", "October", "24,", "2022", "\u2013", "2:00", "pm", "in", "DBH", "3011", "Vijay", "V.", "Vazirani", "(UC", "Irvine)", "LP-Duality", "Theory", "and", "the", "Core", "of", "Game", "October", "13,", "2022", "\u2013", "4:00", "pm", "in", "DBH", "4011", "Prave", "h", "Kothari", "(CMU)", "Robu", "t", "Learning", "of", "Mixture", "of", "Gau", "ian", "October", "6,", "2022", "\u2013", "4:00", "pm", "in", "DBH", "4011", "Venkate", "an", "Guru", "wami", "(UC", "Berkeley)", "A", "Near-cubic", "Lower", "Bound", "for", "3-query", "Locally", "Decodable", "Code", "September", "29,", "2022", "\u2013", "4:00", "pm", "in", "DBH", "4011", "Aranyak", "Mehta", "(Google", "Re", "earch)", "Auto-Bidding,", "Auction", ",", "and", "Allocation", "in", "Internet", "Adverti", "ing:", "Fundamental", "re", "ult", "and", "new", "trend", ".", "September", "9,", "2022", "\u2013", "3:00", "pm", "in", "DBH", "4011", "Jo", "eph", "Cheriyan", "(Univer", "ity", "of", "Waterloo)", "Approximation", "Algorithm", "for", "Network", "De", "ign", "Spring", "2022", "May", "26,", "2022", "\u2013", "4:00", "pm", "in", "DBH", "4011", "Federico", "Echenique", "(Caltech)", "Efficiency", "and", "Fairne", "in", "Random", "Re", "ource", "Allocation", "and", "Social", "Choice", "May", "12,", "2022", "\u2013", "4:00", "pm", "in", "DBH", "4011", "Rajan", "Udwani", "(UC", "Berkeley)", "From", "Adword", "to", "Online", "Matching", "with", "Stocha", "tic", "Reward", ",", "and", "Back", "April", "28,", "2022", "\u2013", "4:00", "pm", "in", "DBH", "4011", "Themi", "Gouleaki", "(NUS)", "Sample", "Efficient", "Di", "tribution", "Te", "ting", "U", "ing", "Centralized", "or", "Di", "tributed", "Computation", "April", "22,", "2022", "\u2013", "2:00", "pm", "in", "DBH", "4011", "Vijay", "Vazirani", "(UCI)", "New", "In", "ight", "into", "the", "Cla", "ic", "Shapley-Shubik", "Work:", "the", "Core", "of", "the", "Matching", "Game", "April", "21,", "2022", "\u2013", "4:00", "pm", "in", "DBH", "4011", "Paul", "Valiant", "(Purdue", "Univer", "ity)", "Mean", "E", "timation", "in", "Low", "and", "High", "Dimen", "ion", "April", "14,", "2022", "\u2013", "4:00", "pm", "in", "DBH", "4011", "Co", "ti", "Da", "kalaki", "(MIT)", "Equilibrium", "Computation", "and", "Machine", "Learning", "March", "31,", "2022", "\u2013", "4:00", "pm", "in", "DBH", "4011", "Eric", "Vigoda", "(UC", "Santa", "Barbara)", "Computational", "pha", "e", "tran", "ition", "and", "MCMC", "algorithm", "Winter", "2022", "March", "10,", "2022", "\u2013", "4:00", "pm", "in", "Zoom", "\u2013", "http", "://uci.zoom.u", "/j/94755690267", "Will", "Ma", "(Columbia)", "Tight", "Multi-unit", "Prophet", "Inequalitie", ",", "with", "Application", "to", "Online", "Allocation", "March", "3,", "2022", "\u2013", "4:00", "pm", "in", "DBH", "4011", "Rachel", "Cumming", "(Columbia)", "Mean", "E", "timation", "with", "U", "er-level", "Privacy", "under", "Data", "Heterogeneity", "February", "24,", "2022", "\u2013", "4:00", "pm", "in", "DBH", "4011", "Leonard", "J.", "Schulman", "(Caltech)", "Parametric", "learning", "for", "directed", "graphical", "model", "February", "17,", "2022", "\u2013", "4:00", "pm", "in", "DBH", "4011", "Urmila", "Mahadev", "(California", "In", "titute", "of", "Technology)", "Efficient", "Certifiable", "Randomne", "February", "10,", "2022", "\u2013", "4:00", "pm", "in", "Zoom", "\u2013", "http", "://uci.zoom.u", "/j/91053519379", "Manoli", "Vlataki", "(Columbia/UC", "Berkeley)", "Building", "Optimization", "beyond", "Minimization:", "A", "Journey", "in", "Game", "Dynamic", ".", "February", "3,", "2022", "\u2013", "2:00", "pm", "in", "Zoom", "\u2013", "http", "://uci.zoom.u", "/j/96921158546", "Pierre", "Baldi", "(UCI)", "The", "Quark", "of", "Attention", "Fall", "2021", "November", "11,", "2021", "\u2013", "11:00", "am", "in", "Zoom", "\u2013", "http"], "content_hash": "6abb1ca8d28dddd3c7de4f1aa8b70f23"}