{"url": "https://vision.ics.uci.edu/papers/YangR_TPAMI_2013", "word_count": 435, "words": ["Computational", "Vi", "ion", "|", "ICS", "|", "UC", "Irvine", "Computational", "Vi", "ion", "at", "UC", "Irvine", "home", "project", "people", "publication", "data", "et", "event", "cour", "e", "contact", "link", "Articulated", "po", "e", "e", "timation", "with", "flexible", "mixture", "-of-part", "Yi", "Yang", ",", "Deva", "Ramanan", "We", "de", "cribe", "a", "method", "for", "articulated", "human", "detection", "and", "human", "po", "e", "e", "timation", "in", "tatic", "image", "ba", "ed", "on", "a", "new", "repre", "entation", "of", "deformable", "part", "model", ".", "Rather", "than", "modeling", "articulation", "u", "ing", "a", "family", "of", "warped", "(rotated", "and", "fore", "hortened)", "template", ",", "we", "u", "e", "a", "mixture", "of", "mall,", "non-oriented", "part", ".", "We", "de", "cribe", "a", "general,", "flexible", "mixture", "model", "that", "jointly", "capture", "patial", "relation", "between", "part", "location", "and", "co-occurrence", "relation", "between", "part", "mixture", ",", "augmenting", "tandard", "pictorial", "tructure", "model", "that", "encode", "ju", "t", "patial", "relation", ".", "Our", "model", "have", "everal", "notable", "propertie", ":", "(1)", "they", "efficiently", "model", "articulation", "by", "haring", "computation", "acro", "imilar", "warp", "(2)", "they", "efficiently", "model", "an", "exponentially-large", "et", "of", "global", "mixture", "through", "compo", "ition", "of", "local", "mixture", "and", "(3)", "they", "capture", "the", "dependency", "of", "global", "geometry", "on", "local", "appearance", "(part", "look", "different", "at", "different", "location", ").", "When", "relation", "are", "tree-", "tructured,", "our", "model", "can", "be", "efficiently", "optimized", "with", "dynamic", "programming.", "We", "learn", "all", "parameter", ",", "including", "local", "appearance", ",", "patial", "relation", ",", "and", "co-occurrence", "relation", "(which", "encode", "local", "rigidity)", "with", "a", "tructured", "SVM", "olver.", "Becau", "e", "our", "model", "i", "efficient", "enough", "to", "be", "u", "ed", "a", "a", "detector", "that", "earche", "over", "cale", "and", "image", "location", ",", "we", "introduce", "novel", "criteria", "for", "evaluating", "po", "e", "e", "timation", "and", "human", "detection,", "both", "eparately", "and", "jointly.", "We", "how", "that", "currently-u", "ed", "evaluation", "criteria", "may", "conflate", "the", "e", "two", "i", "ue", ".", "Mo", "t", "previou", "approache", "model", "limb", "with", "rigid", "and", "articulated", "template", "that", "are", "trained", "independently", "of", "each", "other,", "while", "we", "pre", "ent", "an", "exten", "ive", "diagno", "tic", "evaluation", "that", "ugge", "t", "that", "flexible", "tructure", "and", "joint", "training", "are", "crucial", "for", "trong", "performance.", "We", "pre", "ent", "experimental", "re", "ult", "on", "tandard", "benchmark", "that", "ugge", "t", "our", "approach", "i", "the", "tate-of-the-art", "y", "tem", "for", "po", "e", "e", "timation,", "improving", "pa", "t", "work", "on", "the", "challenging", "Par", "e", "and", "Buffy", "data", "et", ",", "while", "being", "order", "of", "magnitude", "fa", "ter.", "Download:", "pdf", "Text", "Reference", "Yi", "Yang", "and", "Deva", "Ramanan.", "Articulated", "po", "e", "e", "timation", "with", "flexible", "mixture", "-of-part", ".", "IEEE", "TPAMI", ",", "2013.", "BibTeX", "Reference", "@ARTICLE{YangR_TPAMI_2013,", "author", "=", "\"Yang,", "Yi", "and", "Ramanan,", "Deva\",", "title", "=", "\"Articulated", "po", "e", "e", "timation", "with", "flexible", "mixture", "-of-part", "\",", "journal", "=", "\"IEEE", "TPAMI\",", "year", "=", "\"2013\",", "tag", "=", "\"grouping\"", "}", "Computational", "Vi", "ion", "|", "School", "of", "Information", "and", "Computer", "Science", "|", "UC", "Irvine", "\u00a9", "2007-2017", "UC", "Irvine"], "content_hash": "d3ddf111c3e783a802259369558ddbe9"}