{"url": "https://grape.ics.uci.edu/wiki/public/attachment/wiki/cs122b-2019-winter-project1/movie-data.sql", "word_count": 80, "words": ["movie-data.", "ql", "on", "c", "122b-2019-winter-project1", "\u2013", "Attachment", "\u2013", "Public", "Login", "Preference", "About", "Trac", "Regi", "ter", "Context", "Navigation", "Back", "to", "c", "122b-2019-winter-project1", "c", "122b-2019-winter-project1", ":", "movie-data.", "ql", "File", "movie-data.", "ql,", "11.5", "MB", "(added", "by", "yicongh1", ",", "7", "year", "ago", ")", "HTML", "preview", "not", "available", ",", "ince", "the", "file", "ize", "exceed", "256.0", "KB.Try", "downloading", "the", "file", "in", "tead.", "Download", "in", "other", "format", ":", "Original", "Format", "Powered", "by", "Trac", "1.5.3", "By", "Edgewall", "Software", ".", "Vi", "it", "the", "Trac", "open", "ource", "project", "at", "http://trac.edgewall.org/"], "content_hash": "ce8b514da191b34e2eb5bbb8194ed886"}