{"url": "http://stairs.ics.uci.edu/news.html", "word_count": 186, "words": ["News", "Toggle", "navigation", "People", "Papers", "News", "News", "August", "30,", "2021", ":", "Congratulations", "to", "Iftekhar\u2019s", "paper", "got", "accepted", "in", "TSE", "2021!", "August", "7,", "2021", ":", "Congratulations", "to", "Tojing\u2019s", "paper", "got", "accepted", "in", "ASE", "2021!", "May", "2,", "2021", ":", "Congratulations", "to", "Jiri\u2019s", "paper", "got", "accepted", "in", "ESEM", "2021!", "December", "20,", "2020", ":", "One", "of", "Iftekhar", "\u2019s", "papers", "got", "accepted", "at", "ICSE", "2021!", "December", "20,", "2020", ":", "Congratulations", "to", "Andrew\u2019s", "first", "ICSE", "paper", "got", "accepted", "in", "ICSE", "2021!", "May", "20,", "2020", ":", "One", "of", "Iftekhar", "\u2019s", "papers", "got", "accepted", "at", "FSE", "2020!", "March", "10,", "2020", ":", "One", "of", "Iftekhar", "\u2019s", "papers", "got", "accepted", "at", "ASE", "2020!", "February", "3,", "2020", ":", "Two", "of", "Iftekhar", "\u2019s", "papers", "got", "accepted", "at", "EASE", "2020!", "December", "8,", "2019", ":", "Two", "of", "Iftekhar", "\u2019s", "papers", "got", "accepted!", "-", "\u2018Planning", "for", "Untangling:", "Predicting", "the", "Difficulty", "of", "Merge", "Conflicts\u2019", "at", "ICSE", "2020", "-", "\u2018Accessibility", "Issues", "in", "Android", "Apps:", "State", "of", "Affairs,", "Sentiments,", "and", "Ways", "Forward\u2019", "at", "ICSE", "2020", "December", "1,", "2019", ":", "One", "of", "Iftekhar", "\u2019s", "papers", "got", "accepted", "at", "TOSEM", "2020!", "September", "23,", "2019", ":", "STAIRS", "Lab", "is", "established!", "University", "of", "California,", "Irvine", "STAIRS", "Lab,", "2024"], "content_hash": "27dfa9592ca0b7de79cfd1043c5e6391"}