{"url": "https://grape.ics.uci.edu/wiki/public/attachment/wiki/cs122b-2018-winter-project2/TomcatForm.war", "word_count": 71, "words": ["TomcatForm.war", "on", "cs122b-2018-winter-project2", "\u2013", "Attachment", "\u2013", "Public", "Login", "Preferences", "About", "Trac", "Register", "Context", "Navigation", "Back", "to", "cs122b-2018-winter-project2", "cs122b-2018-winter-project2", ":", "TomcatForm.war", "File", "TomcatForm.war,", "604.9", "KB", "(added", "by", "Qiushi", "Bai", ",", "8", "years", "ago", ")", "HTML", "preview", "not", "available", ",", "since", "the", "file", "size", "exceeds", "256.0", "KB.Try", "downloading", "the", "file", "instead.", "Download", "in", "other", "formats:", "Original", "Format", "Powered", "by", "Trac", "1.5.3", "By", "Edgewall", "Software", ".", "Visit", "the", "Trac", "open", "source", "project", "at", "http://trac.edgewall.org/"], "content_hash": "5bb8de969e6c0f4e406ffab61f7d3bd5"}