{"url": "https://grape.ics.uci.edu/wiki/public/wiki/cs122b-2017-winter-project3?action=diff&version=4", "word_count": 729, "words": ["cs122b-2017-winter-project3", "(diff)", "\u2013", "Public", "Login", "Preferences", "About", "Trac", "Register", "Context", "Navigation", "\u2190", "Previous", "Change", "Wiki", "History", "Next", "Change", "\u2192", "Changes", "between", "Version", "3", "and", "Version", "4", "of", "cs122b-2017-winter-project3", "View", "differences", "inline", "side", "by", "side", "Show", "lines", "around", "each", "change", "Show", "the", "changes", "in", "full", "context", "Ignore:", "Blank", "lines", "Case", "changes", "White", "space", "changes", "Timestamp:", "Feb", "1,", "2017,", "9:58:06", "PM", "(", "9", "years", "ago)", "Author:", "Chen", "Luo", "Comment:", "--", "Legend:", "Unmodified", "Added", "Removed", "Modified", "cs122b-2017-winter-project3", "v3", "v4", "19", "19", "Improve", "the", "user-authentication", "process", "of", "project", "2", "by", "adding", "a", "module", "that", "verifies", "real", "users", "and", "blocks", "bots.", "20", "20", "21", "1.", "Download", "and", "deploy", "[attachment:wiki:cs122b-2017-winter-project3:TomcatFormReCaptcha.war", "TomcatFormReCaptcha.war].", "21", "22", "1.", "Get", "a", "[https://www.google.com/recaptcha/intro/index.html", "reCAPTCHA]", "from", "Google.", "Use", "the", "public", "IP", "of", "your", "AWS", "instance", "as", "the", "domain.", "You", "will", "get", "a", "''secret", "key''", "and", "a", "''site", "key''.", "22", "1.", "Download", "and", "deploy", "[attachment:wiki:cs122b-2017-winter-project3:TomcatFormReCaptcha.war", "TomcatFormReCaptcha.war].", "23", "1.", "Follow", "the", "instructions", "at", "[https://developers.google.com/recaptcha/docs/secure_token", "here]", "to", "modify", "the", "file", "\"webapps/TomcatFormReCaptcha/index.html\".", "In", "particular,", "use", "your", "own", "\"site", "key\"", "to", "replace", "the", "\"data-sitekey\"", "value.", "23", "1.", "Follow", "the", "instructions", "on", "the", "page", "shown", "in", "step", "2", "to", "modify", "the", "file", "\"webapps/TomcatFormReCaptcha/index.html\".", "In", "particular,", "use", "your", "own", "\"site", "key\"", "to", "replace", "the", "\"data-sitekey\"", "value.", "24", "24", "1.", "Test", "the", "page", "http://YOUR_IP:8080/TomcatFormReCaptcha", "to", "see", "if", "reCAPTHA", "works", "for", "the", "front", "end.", "25", "25", "1.", "Read", "and", "understand", "the", "file", "\"sources/TomcatFormReCaptcha.java\",", "especially", "the", "logic", "related", "to", "verifying", "\"g-recaptcha-response\".", "Also", "modify", "the", "file", "\"!MyConstants.java\"", "to", "use", "your", "own", "\"SITE_KEY\"", "and", "\"SECRET_KEY\"", "values.", "\u2026", "\u2026", "106", "106", "As", "shown", "in", "Figure", "1,", "the", "root", "tag", "in", "the", "file", "`mains243.xml`", "is", "`<movies>`,", "which", "consists", "of", "several", "instances", "of", "the", "tag", "`<directorfilms>`.", "Each", "`<directorfilms>`", "contains", "the", "information", "of", "a", "director,", "along", "with", "his/her", "movies,", "each", "movie", "being", "an", "instance", "of", "the", "tag", "`<film>`.", "It", "is", "clear", "where", "to", "find", "the", "values", "of", "all", "the", "columns", "of", "the", "movies", "table,", "except", "for", "the", "`banner_url`", "and", "`trailer_url`", "values", "that", "should", "be", "left", "NULL.", "Furthermore,", "each", "<film>", "has", "a", "list", "of", "''assigned", "categories", "''in", "a", "`<cats>`", "tag", "(i.e.,", "each", "category", "as", "a", "`<cat>`", "tag).", "The", "value", "of", "the", "`<cat>`", "tag", "corresponds", "to", "the", "genre", "name", "in", "the", "`genres`", "table", "of", "the", "Fabflix", "database.", "If", "a", "`<cat>`", "does", "not", "exist", "in", "the", "`genres`", "table,", "a", "new", "genre", "must", "be", "added,", "and", "the", "`genres_in_movies`", "table", "must", "be", "updated", "accordingly.", "107", "107", "108", "[[Image(wiki:cs122b-2017-winter-project", "4", ":films_structure.png)]]", "'''Figure", "1.'''", "108", "[[Image(wiki:cs122b-2017-winter-project", "3", ":films_structure.png)]]", "'''Figure", "1.'''", "109", "109", "110", "110", "For", "updating", "the", "`stars`", "and", "`stars_in_movies`", "tables,", "you", "should", "use", "the", "content", "of", "the", "file", "`casts124.xml`,", "which", "is", "shown", "in", "a", "high-level", "view", "in", "Figure", "2.", "111", "111", "112", "[[Image(wiki:cs122b-2017-winter-project", "4", ":casts_structure.png)]]", "'''Figure", "2.'''", "112", "[[Image(wiki:cs122b-2017-winter-project", "3", ":casts_structure.png)]]", "'''Figure", "2.'''", "113", "113", "114", "114", "Similar", "to", "the", "`<movies>`", "tag,", "the", "content", "of", "the", "`<casts>`", "tag,", "which", "is", "the", "root", "of", "the", "file", "`casts124.xml`,", "is", "also", "grouped", "by", "the", "movie", "directors.", "You", "can", "find", "the", "information", "of", "the", "star-movie", "connections", "in", "the", "instances", "of", "the", "`<m>`", "tag.", "In", "this", "tag,", "the", "film", "is", "identified", "using", "the", "`<f>`", "tag,", "which", "links", "to", "the", "`<fid>", "`tag", "of", "the", "`<film>`", "tag", "in", "the", "main", "file.", "Tag", "`<m>`", "also", "gives", "you", "the", "`stagename`", "of", "the", "actor", "of", "this", "relation", "in", "a", "tag", "called", "`<a>`.", "The", "`stagename`", "helps", "you", "connect", "this", "`stars_in_movies`", "record", "to", "the", "right", "star", "record.", "The", "stars", "to", "be", "added", "to", "the", "`stars`", "table", "are", "parsed", "out", "of", "the", "file", "`actors63.xml`.", "Except", "for", "the", "`photo_url`", "column", "of", "the", "`stars`", "table", "that", "should", "be", "left", "NULL,", "it", "is", "clear", "how", "to", "use", "the", "actors", "file", "to", "populate", "this", "table.", "\u2026", "\u2026", "118", "118", "===", "Requirements:", "===", "119", "119", "*", "'''XML", "parsing''':", "You", "should", "write", "a", "Java", "program", "to", "parse", "the", "XML", "files", "and", "populate", "the", "database.", "120", "*", "'''Performance", "Tuning''':", "A", "naive", "implementation", "of", "your", "program", "is", "expected", "to", "be", "slow.", "Come", "up", "with", "at", "least", "two", "optimization", "techniques", "to", "reduce", "the", "running", "time", "of", "your", "program.", "Write", "an", "itemized,", "brief", "report", "accessible", "at", "the", "link", "http://YOUR_PUBLIC_IP:8080/fabflix/reports/xml_parsing_optimization", "to", "describe", "your", "optimizations,", "and", "the", "corresponding", "time", "reductions.[[BR]]", "120", "*", "'''Performance", "Tuning''':", "A", "naive", "implementation", "of", "your", "program", "is", "expected", "to", "be", "slow.", "Come", "up", "with", "at", "least", "two", "optimization", "techniques", "to", "reduce", "the", "running", "time", "of", "your", "program.", "Write", "an", "itemized,", "brief", "report", "accessible", "to", "describe", "your", "optimizations,", "and", "the", "corresponding", "time", "reductions.[[BR]]", "121", "121", "122", "122", "===", "Remarks:", "===", "Powered", "by", "Trac", "1.5.3", "By", "Edgewall", "Software", ".", "Visit", "the", "Trac", "open", "source", "project", "at", "http://trac.edgewall.org/"], "content_hash": "7cfdb9f9343a98a88bcf2b681556a2dd"}